qtrename/About.py
qtrename/Animation.py
qtrename/Errors.py
qtrename/TableView.py
qtrename/Theme.py
qtrename/__init__.py
qtrename/__main__.py
qtrename/add_remove.py
qtrename/app.png
qtrename/casing.py
qtrename/common.py
qtrename/counters.py
qtrename/main.py
qtrename/mainwindow.py
qtrename/move.py
qtrename/preview.py
qtrename/qtrenamer_rc.py
qtrename/replace.py
qtrename/spaces.py
qtrename/worker.py
qtrename-1.1.1.dist-info/LICENSE
qtrename-1.1.1.dist-info/METADATA
qtrename-1.1.1.dist-info/WHEEL
qtrename-1.1.1.dist-info/entry_points.txt
qtrename-1.1.1.dist-info/top_level.txt
qtrename-1.1.1.dist-info/RECORD
