Metadata-Version: 2.1
Name: qtrename
Version: 1.1.1
Summary: feature-rich app to rename files for GNU/Linux and Windows
Home-page: https://github.com/amad3v/QtRename
Author: Mohamed Jouini
Author-email: amad3v@gmail.com
License: UNKNOWN
Project-URL: Bug Reports, https://github.com/amad3v/QtRename/issues
Project-URL: Releases, https://github.com/amad3v/QtRename/releases
Platform: UNKNOWN
Classifier: Development Status :: 5 - Production/Stable
Classifier: Environment :: X11 Applications :: Qt
Classifier: Intended Audience :: End Users/Desktop
Classifier: License :: OSI Approved :: GNU General Public License v3 or later (GPLv3+)
Classifier: Operating System :: POSIX :: Linux
Classifier: Operating System :: Microsoft :: Windows
Classifier: Programming Language :: Python :: 3.7
Classifier: Topic :: Utilities
Requires-Python: >=3.7
Requires-Dist: PyQt5 (>=5.13.2)
